2005/ii_4.v
module ii_4(clk, count, reset, c0, c1, c2, c3);
	input clk, count, reset;
	output reg c0, c1, c2, c3;

	wire calc_c0, calc_c1, calc_c2, calc_c3;
	assign calc_c0 = (count & ~c0) | (~count & c0);
	assign calc_c1 =
		((count & c0) & ~c1) |
		((~count | ~c0) & c1);
	assign calc_c2 =
		((count & c0 & c1) & ~c2) |
		((~count | ~c0 | ~c1) & c2);
	assign calc_c3 =
		((count & c0 & c1 & c2) & ~c3) |
		((~count | ~c0 | ~c1 | ~c2) & c3);

	wire reset_by_limit;
	assign reset_by_limit = c0 & ~c1 & c2 & c3;
	wire reset_final;
	assign reset_final = reset | reset_by_limit;

	wire next_c0, next_c1, next_c2, next_c3;
	assign next_c0 = calc_c0 & ~reset_final;
	assign next_c1 = calc_c1 & ~reset_final;
	assign next_c2 = calc_c2 & ~reset_final;
	assign next_c3 = calc_c3 & ~reset_final;

	always @(posedge clk) begin
		c0 <= next_c0;
		c1 <= next_c1;
		c2 <= next_c2;
		c3 <= next_c3;
	end

	initial begin
		c0 = 0; c1 = 0; c2 = 0; c3 = 0;
	end
endmodule

2005/ii_4_tb.v
module ii_4_tb();
	reg clk, count, reset;
	wire c0, c1, c2, c3;

	ii_4 ii_4i(clk, count, reset, c0, c1, c2, c3);

	initial begin
		clk = 0; count = 1; reset = 0;
		#510 reset <= 1;
		#550 reset <= 0;
		#590 count <= 0;
		#630 count <= 1;
		#1000 $finish;
	end
	always #10 clk <= ~clk;

	initial begin
		$dumpfile("ii_4.vcd");
		$dumpvars(0, ii_4_tb);
	end
endmodule

2005/ii_4.vcd
$date
	Sun Feb 23 15:45:17 2025
$end
$version
	Icarus Verilog
$end
$timescale
	1s
$end
$scope module ii_4_tb $end
$var wire 1 ! c3 $end
$var wire 1 " c2 $end
$var wire 1 # c1 $end
$var wire 1 $ c0 $end
$var reg 1 % clk $end
$var reg 1 & count $end
$var reg 1 ' reset $end
$scope module ii_4i $end
$var wire 1 ( calc_c0 $end
$var wire 1 ) calc_c1 $end
$var wire 1 * calc_c2 $end
$var wire 1 + calc_c3 $end
$var wire 1 % clk $end
$var wire 1 & count $end
$var wire 1 , next_c0 $end
$var wire 1 - next_c1 $end
$var wire 1 . next_c2 $end
$var wire 1 / next_c3 $end
$var wire 1 ' reset $end
$var wire 1 0 reset_by_limit $end
$var wire 1 1 reset_final $end
$var reg 1 $ c0 $end
$var reg 1 # c1 $end
$var reg 1 " c2 $end
$var reg 1 ! c3 $end
$upscope $end
$upscope $end
$enddefinitions $end
$comment Show the parameter values. $end
$dumpall
$end
#0
$dumpvars
01
00
0/
0.
0-
1,
0+
0*
0)
1(
0'
1&
0%
0$
0#
0"
0!
$end
#10
1-
0,
1)
0(
1$
1%
#20
0%
#30
1-
1,
1)
1(
1#
0$
1%
#40
0%
#50
1.
0-
1*
0)
0,
0(
1$
1%
#60
0%
#70
1.
1,
1*
1(
1"
0#
0$
1%
#80
0%
#90
1-
0,
1)
0(
1$
1%
#100
0%
#110
1-
1,
1)
1(
1#
0$
1%
#120
0%
#130
1/
0.
1+
0*
0-
0)
0,
0(
1$
1%
#140
0%
#150
1/
1,
1+
1(
1!
0"
0#
0$
1%
#160
0%
#170
1-
0,
1)
0(
1$
1%
#180
0%
#190
1-
1,
1)
1(
1#
0$
1%
#200
0%
#210
1.
0-
1*
0)
0,
0(
1$
1%
#220
0%
#230
1.
1,
1*
1(
1"
0#
0$
1%
#240
0%
#250
0.
0/
11
0-
0,
10
1)
0(
1$
1%
#260
0%
#270
1,
0)
1(
01
0+
0*
00
0!
0"
0$
1%
#280
0%
#290
1-
0,
1)
0(
1$
1%
#300
0%
#310
1-
1,
1)
1(
1#
0$
1%
#320
0%
#330
1.
0-
1*
0)
0,
0(
1$
1%
#340
0%
#350
1.
1,
1*
1(
1"
0#
0$
1%
#360
0%
#370
1-
0,
1)
0(
1$
1%
#380
0%
#390
1-
1,
1)
1(
1#
0$
1%
#400
0%
#410
1/
0.
1+
0*
0-
0)
0,
0(
1$
1%
#420
0%
#430
1/
1,
1+
1(
1!
0"
0#
0$
1%
#440
0%
#450
1-
0,
1)
0(
1$
1%
#460
0%
#470
1-
1,
1)
1(
1#
0$
1%
#480
0%
#490
1.
0-
1*
0)
0,
0(
1$
1%
#500
0%
#510
1*
1(
1"
0#
0$
0.
0/
11
1%
1'
#520
0%
#530
0+
0*
0!
0"
1%
