2008/ii_4_2.v
module ii_4_2(x3, x2, x1, x0, l1, l0, z);
	input x3, x2, x1, x0;
	output l1, l0, z;

	assign l1 =
		~x0 & ~x1 & (x2 | x3);
	assign l0 =
		~x0 & x1  | ~x0 & ~x1 & ~x2 & x3;
	assign z = ~x3 & ~x2 & ~x1 & ~x0;
endmodule

2008/ii_4_2_tb.v
module ii_4_tb();
	reg x3, x2, x1, x0;
	wire l1, l0, z;

	ii_4_2 ii_4_2(x3, x2, x1, x0, l1, l0, z);

	initial begin
		x3 = 0; x2 = 0; x1 = 0; x0 = 0;
		#10 x3 <= 1;
		#10 x2 <= 1;
		#10 x1 <= 1;
		#10 x0 <= 1;
		#10 x2 <= 0;
		#10 x0 <= 0;
		#10 x3 <= 0;
		#10 x1 <= 0;
		$finish;
	end

	initial begin
		$dumpfile("ii_4_2.vcd");
		$dumpvars(0, ii_4_tb);
	end
endmodule

2008/ii_4_2.vcd
$date
	Mon Feb 24 00:26:30 2025
$end
$version
	Icarus Verilog
$end
$timescale
	1s
$end
$scope module ii_4_tb $end
$var wire 1 ! z $end
$var wire 1 " l1 $end
$var wire 1 # l0 $end
$var reg 1 $ x0 $end
$var reg 1 % x1 $end
$var reg 1 & x2 $end
$var reg 1 ' x3 $end
$scope module ii_4_2 $end
$var wire 1 # l0 $end
$var wire 1 " l1 $end
$var wire 1 $ x0 $end
$var wire 1 % x1 $end
$var wire 1 & x2 $end
$var wire 1 ' x3 $end
$var wire 1 ! z $end
$upscope $end
$upscope $end
$enddefinitions $end
$comment Show the parameter values. $end
$dumpall
$end
#0
$dumpvars
0'
0&
0%
0$
0#
0"
1!
$end
#10
0!
1"
1#
1'
#20
0#
1&
#30
0"
1#
1%
#40
0#
1$
#50
0&
#60
1#
0$
#70
0'
#80
1!
0#
0%
